[
  {
    "ContainingType": "PA_BACKEND.Controllers.AuditLogController",
    "Method": "GetAuditLogs",
    "RelativePath": "api/AuditLog",
    "HttpMethod": "GET",
    "IsController": true,
    "Order": 0,
    "Parameters": [
      {
        "Name": "userId",
        "Type": "System.Nullable\u00601[[System.Int32, System.Private.CoreLib, Version=8.0.0.0, Culture=neutral, PublicKeyToken=7cec85d7bea7798e]]",
        "IsRequired": false
      },
      {
        "Name": "action",
        "Type": "System.String",
        "IsRequired": false
      },
      {
        "Name": "entityType",
        "Type": "System.String",
        "IsRequired": false
      },
      {
        "Name": "entityId",
        "Type": "System.Nullable\u00601[[System.Int32, System.Private.CoreLib, Version=8.0.0.0, Culture=neutral, PublicKeyToken=7cec85d7bea7798e]]",
        "IsRequired": false
      },
      {
        "Name": "ipAddress",
        "Type": "System.String",
        "IsRequired": false
      },
      {
        "Name": "dateFrom",
        "Type": "System.Nullable\u00601[[System.DateTime, System.Private.CoreLib, Version=8.0.0.0, Culture=neutral, PublicKeyToken=7cec85d7bea7798e]]",
        "IsRequired": false
      },
      {
        "Name": "dateTo",
        "Type": "System.Nullable\u00601[[System.DateTime, System.Private.CoreLib, Version=8.0.0.0, Culture=neutral, PublicKeyToken=7cec85d7bea7798e]]",
        "IsRequired": false
      },
      {
        "Name": "limit",
        "Type": "System.Int32",
        "IsRequired": false
      },
      {
        "Name": "offset",
        "Type": "System.Int32",
        "IsRequired": false
      }
    ],
    "ReturnTypes": []
  },
  {
    "ContainingType": "PA_BACKEND.Controllers.GatewayController",
    "Method": "Process",
    "RelativePath": "api/Gateway",
    "HttpMethod": "POST",
    "IsController": true,
    "Order": 0,
    "Parameters": [
      {
        "Name": "request",
        "Type": "PA_BACKEND.DTOs.Common.GatewayRequestDTO",
        "IsRequired": true
      }
    ],
    "ReturnTypes": []
  }
]